LICENSE
MANIFEST.in
README.md
sample.yaml
setup.cfg
setup.py
xFlow.egg-info/PKG-INFO
xFlow.egg-info/SOURCES.txt
xFlow.egg-info/dependency_links.txt
xFlow.egg-info/entry_points.txt
xFlow.egg-info/not-zip-safe
xFlow.egg-info/requires.txt
xFlow.egg-info/top_level.txt
xflow/__init__.py
xflow/aws.py
xflow/core.py
xflow/schema.yaml
xflow/server.py
xflow/tracker.py
xflow/utils.py