Metadata-Version: 1.1
Name: xFlow
Version: 0.1.12
Summary: A serverless workflow architecture using AWS Lambda functions and Kinesis
Home-page: http://github.com/dsouzajude/xFlow
Author: Jude D'Souza
Author-email: dsouza_jude@hotmail.com
License: UNKNOWN
Download-URL: https://github.com/dsouzajude/xflow/archive/0.1.tar.gz
Keywords: serverless,lambda,kinesis,workflow,streams,eventbus
Platform: UNKNOWN
Classifier: Intended Audience :: Developers
Classifier: Operating System :: OS Independent
Classifier: Environment :: Console
Classifier: Programming Language :: Python
Classifier: Programming Language :: Python :: 2.7
Classifier: Programming Language :: Python :: 3
Classifier: Programming Language :: Python :: 3.3
Classifier: Programming Language :: Python :: 3.4
